slackviews/__init__.py
slackviews/payloads.py
slackviews/view.py
slackviews-1.1.2.dist-info/LICENSE
slackviews-1.1.2.dist-info/METADATA
slackviews-1.1.2.dist-info/WHEEL
slackviews-1.1.2.dist-info/top_level.txt
slackviews-1.1.2.dist-info/RECORD
