Metadata-Version: 2.1
Name: slackviews
Version: 1.1.2
Summary: Project with a library to generate Slack views from code, using builder pattern
Home-page: https://github.com/escamez/slackviews
Author: Agustin Escamez
Author-email: aech22@gmail.com
License: MIT
Download-URL: https://github.com/escamez/slackviews/archive/v1.1.2.tar.gz
Keywords: slack,views,modals,blocks
Platform: UNKNOWN
Classifier: Intended Audience :: Developers
Classifier: Programming Language :: Python :: 3
Classifier: Operating System :: OS Independent
Classifier: License :: OSI Approved :: MIT License
Classifier: Topic :: Communications :: Chat
Classifier: Topic :: System :: Networking
Classifier: Topic :: Office/Business
Requires-Python: >=3.6
